Metadata-Version: 2.1
Name: dinglingling
Version: 0.1.0
Summary: remind you the status of the program
Home-page: https://github.com/PeijiYang/dinglingling
Author: Peiji
Author-email: peiji.yang@foxmail.com
License: MIT
Platform: UNKNOWN
Classifier: Intended Audience :: Science/Research
Classifier: Development Status :: 3 - Alpha
Classifier: License :: OSI Approved :: MIT License
Classifier: Programming Language :: Python :: 3.7
Classifier: Topic :: Scientific/Engineering :: Artificial Intelligence
Requires-Python: >=3.6
